setup.py
readypipe/__init__.py
readypipe.egg-info/PKG-INFO
readypipe.egg-info/SOURCES.txt
readypipe.egg-info/dependency_links.txt
readypipe.egg-info/not-zip-safe
readypipe.egg-info/top_level.txt