Metadata-Version: 1.1
Name: readypipe
Version: 0.0.1
Summary: readypipe
Home-page: http://www.readypipe.io/
Author: Yipit Coders
Author-email: coders@yipitdata.com
License: UNKNOWN
Platform: UNKNOWN
Classifier: Programming Language :: Python
